<configs>
	<append xpath="/items">
		<item name="vdshkoKitchenSinkSchematic">
			<property name="Extends" value="schematicNoQualityMaster"/>
			<property name="DescriptionKey" value="vdshkoKitchenSinkSchematicDesc"/>
			<property name="CreativeMode" value="Player"/>
			<property name="CustomIcon" value="vdshkoKitchenSinkSchematic"/>
			<property name="CustomIconTint" value="873e23"/>
			<property name="Unlocks" value="vdshkoKitchenSink"/>
			<effect_group tiered="false">
				<triggered_effect trigger="onSelfPrimaryActionEnd" action="ModifyCVar" cvar="vdshkoKitchenSinkSchematic" operation="set" value="1"/>
				<triggered_effect trigger="onSelfPrimaryActionEnd" action="GiveExp" exp="50"/>
			</effect_group>
		</item>
		
		<item name="vdshkoKitchenWaterFreezerSchematic">
			<property name="Extends" value="schematicNoQualityMaster"/>
			<property name="DescriptionKey" value="vdshkoKitchenWaterFreezerSchematicDesc"/>
			<property name="CreativeMode" value="Player"/>
			<property name="CustomIcon" value="cntFreezerBeveragesMiddleFullClosed"/>
			<property name="CustomIconTint" value="873e23"/>
			<property name="Unlocks" value="vdshkoKitchenWaterFreezer"/>
			<effect_group tiered="false">
				<triggered_effect trigger="onSelfPrimaryActionEnd" action="ModifyCVar" cvar="vdshkoKitchenWaterFreezerSchematic" operation="set" value="1"/>
				<triggered_effect trigger="onSelfPrimaryActionEnd" action="GiveExp" exp="50"/>
			</effect_group>
		</item>
		
		<item name="vdshkoKitchenStoveSchematic">
			<property name="Extends" value="schematicNoQualityMaster"/>
			<property name="DescriptionKey" value="vdshkoKitchenStoveSchematicDesc"/>
			<property name="CreativeMode" value="Player"/>
			<property name="CustomIcon" value="cntWallOven"/>
			<property name="CustomIconTint" value="873e23"/>
			<property name="Unlocks" value="vdshkoKitchenStove"/>
			<effect_group tiered="false">
				<triggered_effect trigger="onSelfPrimaryActionEnd" action="ModifyCVar" cvar="vdshkoKitchenStoveSchematic" operation="set" value="1"/>
				<triggered_effect trigger="onSelfPrimaryActionEnd" action="GiveExp" exp="50"/>
			</effect_group>
		</item>
		
		<item name="vdshkoBrassPlumbing">
			<property name="DescriptionKey" value="vdshkoBrassPlumbingDesc"/>
			<property name="Meshfile" value="#Other/Items?Misc/sackPrefab.prefab"/>
			<property name="DropMeshfile" value="#Other/Items?Misc/sack_droppedPrefab.prefab"/>
			<property name="Material" value="MresourceScrapBrassSmall"/>
			<property name="MeltTimePerUnit" value=".4"/>
			<property name="Stacknumber" value="6000"/>
			<property name="EconomicValue" value="30"/>
			<property name="Group" value="Resources"/>
		</item>
	</append>
	
	<setattribute xpath="/items/item[@name='toolForgeCrucible' or @name='foodRottingFlesh']/property[@name='SellableToTrader']" name="value">true</setattribute>
</configs>